py_app_standalone/__init__.py
py_app_standalone/build.py
py_app_standalone/cli.py
py_app_standalone/cli_utils.py
py_app_standalone/py.typed
py_app_standalone/search_replace_files.py
py_app_standalone/shebangs.py
py_app_standalone-0.2.1.dist-info/METADATA
py_app_standalone-0.2.1.dist-info/WHEEL
py_app_standalone-0.2.1.dist-info/entry_points.txt
py_app_standalone-0.2.1.dist-info/licenses/LICENSE
py_app_standalone-0.2.1.dist-info/RECORD
