Metadata-Version: 2.4
Name: py-app-standalone
Version: 0.2.1
Summary: Use uv to build a standalone, relocatable Python installation with the given packages installed
Project-URL: Repository, https://github.com/jlevy/py-app-standalone
Author-email: Joshua Levy <joshua@cal.berkeley.edu>
License-Expression: MIT
License-File: LICENSE
Classifier: Development Status :: 4 - Beta
Classifier: Intended Audience :: Developers
Classifier: Operating System :: OS Independent
Classifier: Programming Language :: Python
Classifier: Programming Language :: Python :: 3
Classifier: Programming Language :: Python :: 3.12
Classifier: Programming Language :: Python :: 3.13
Classifier: Typing :: Typed
Requires-Python: >=3.13.2
Requires-Dist: funlog>=0.2.1
Requires-Dist: prettyfmt>=0.3.0
Requires-Dist: rich-argparse>=1.7.0
Requires-Dist: rich>=14.0.0
Requires-Dist: strif>=2.1.0
